scriber/__init__.py
scriber/cli.py
scriber/config.py
scriber/core.py
project_scriber-1.1.2.dist-info/METADATA
project_scriber-1.1.2.dist-info/WHEEL
project_scriber-1.1.2.dist-info/entry_points.txt
project_scriber-1.1.2.dist-info/licenses/LICENSE
project_scriber-1.1.2.dist-info/RECORD
