Metadata-Version: 2.4
Name: project-scriber
Version: 1.1.2
Summary: An intelligent tool to map, analyze, and compile project source code for LLM context.
Project-URL: Homepage, https://github.com/SunneV/ProjectScriber
Project-URL: Issues, https://github.com/SunneV/ProjectScriber/issues
Author-email: "SunneV (Wojciech Mariusz Cichoń)" <wojciech.m.cichon@gmail.com>
License: MIT License
License-File: LICENSE
Keywords: code-analysis,context-builder,developer-tools,llm,source-code
Classifier: License :: OSI Approved :: MIT License
Classifier: Operating System :: OS Independent
Classifier: Programming Language :: Python :: 3
Classifier: Topic :: Software Development :: Libraries :: Python Modules
Classifier: Topic :: Utilities
Requires-Python: >=3.10
Requires-Dist: pathspec
Requires-Dist: pyperclip
Requires-Dist: python-dotenv
Requires-Dist: tiktoken
Requires-Dist: tomli; python_version < '3.11'
Requires-Dist: tomlkit
Provides-Extra: dev
Requires-Dist: pytest; extra == 'dev'
Requires-Dist: pytest-mock; extra == 'dev'
Requires-Dist: rich; extra == 'dev'
Provides-Extra: rich
Requires-Dist: rich; extra == 'rich'
